{
  "version": "0.6.9",
  "period": "2026-05-22",
  "source_url": "https://raw.githubusercontent.com/aqua5230/usage/main/CHANGELOG.md",
  "fetched_at": "2026-07-14",
  "entries": [
    "**New \"Cloud Observation\" panel**: fifth built-in panel with a weather-station visual — light blue sky gradient, white cloud layers (with `feGaussianBlur` soft edges), pale contour lines, and translucent glass cards. Light overall tone, with `backdrop-filter` letting the clouds peek through. Adds i18n key `panel_cloud_observation` (all 5 languages)."
  ]
}
